alita/__init__.py
alita/app.py
alita/base.py
alita/blueprints.py
alita/cli.py
alita/config.py
alita/constants.py
alita/converters.py
alita/datastructures.py
alita/exceptions.py
alita/factory.py
alita/handler.py
alita/helpers.py
alita/request.py
alita/response.py
alita/routing.py
alita/signals.py
alita/templating.py
alita/utils.py
alita/worker.py
alita/serve/__init__.py
alita/serve/config.py
alita/serve/reloader.py
alita/serve/server.py
alita/serve/utils.py
alita/serve/ws.py
alita-0.2.3.dist-info/METADATA
alita-0.2.3.dist-info/RECORD
alita-0.2.3.dist-info/WHEEL
alita-0.2.3.dist-info/entry_points.txt
alita-0.2.3.dist-info/top_level.txt
